xaal/__init__.py
xaal/metadb/__init__.py
xaal/metadb/__main__.py
xaal/metadb/app.py
xaal_metadb-0.1.2.dist-info/METADATA
xaal_metadb-0.1.2.dist-info/WHEEL
xaal_metadb-0.1.2.dist-info/top_level.txt
xaal_metadb-0.1.2.dist-info/RECORD
